django_yt_logviewer-0.1.2.dist-info/licenses/LICENSE
logviewer/__init__.py
logviewer/apps.py
logviewer/site.py
logviewer/templates/logviewer.html
django_yt_logviewer-0.1.2.dist-info/METADATA
django_yt_logviewer-0.1.2.dist-info/WHEEL
django_yt_logviewer-0.1.2.dist-info/top_level.txt
django_yt_logviewer-0.1.2.dist-info/RECORD
